sthg_base_common/__init__.py
sthg_base_common/base_code/__init__.py
sthg_base_common/base_code/exception.py
sthg_base_common/base_code/httpCodeEnmu.py
sthg_base_common/base_code/response.py
sthg_base_common/example/__init__.py
sthg_base_common/example/test_fastapi.py
sthg_base_common/example/test_service.py
sthg_base_common/example/test_utils.py
sthg_base_common/utils/__init__.py
sthg_base_common-0.1.3.dist-info/METADATA
sthg_base_common-0.1.3.dist-info/WHEEL
sthg_base_common-0.1.3.dist-info/top_level.txt
sthg_base_common-0.1.3.dist-info/RECORD
